trame/__init__.py
trame/modules/__init__.py
trame/modules/trame.py
trame/widgets/__init__.py
trame/widgets/trame.py
trame_components/LICENSE
trame_components/__init__.py
trame_components/module/__init__.py
trame_components/module/serve/trame-components.umd.js
trame_components/widgets/__init__.py
trame_components/widgets/trame.py
trame_components-2.5.0.dist-info/LICENSE
trame_components-2.5.0.dist-info/METADATA
trame_components-2.5.0.dist-info/WHEEL
trame_components-2.5.0.dist-info/top_level.txt
trame_components-2.5.0.dist-info/RECORD
