Metadata-Version: 2.1
Name: trame-components
Version: 2.5.0
Summary: Core components for trame widgets
Author: Kitware Inc.
License: Apache License 2.0
Keywords: Python,Interactive,Web,Application,Framework
Classifier: Development Status :: 5 - Production/Stable
Classifier: Environment :: Web Environment
Classifier: License :: OSI Approved :: Apache Software License
Classifier: Natural Language :: English
Classifier: Operating System :: OS Independent
Classifier: Programming Language :: Python :: 3 :: Only
Classifier: Programming Language :: JavaScript
Classifier: Topic :: Software Development :: Libraries :: Application Frameworks
Classifier: Topic :: Software Development :: Libraries :: Python Modules
License-File: LICENSE
